playplaysyn/__init__.py
playplaysyn/__main__.py
playplaysyn/cli/__init__.py
playplaysyn/cli/client.py
playplaysyn/common_utils/__init__.py
playplaysyn/common_utils/concurrent_utils.py
playplaysyn/common_utils/crypto_utils.py
playplaysyn/common_utils/debug_utils.py
playplaysyn/common_utils/type_utils.py
playplaysyn/data_types/__init__.py
playplaysyn/data_types/audio.py
playplaysyn/data_types/box2d.py
playplaysyn/data_types/character.py
playplaysyn/data_types/event.py
playplaysyn/data_types/image.py
playplaysyn/data_types/point2d.py
playplaysyn-0.0.2.dist-info/METADATA
playplaysyn-0.0.2.dist-info/WHEEL
playplaysyn-0.0.2.dist-info/top_level.txt
playplaysyn-0.0.2.dist-info/RECORD
